README.txt
setup.py
collective/__init__.py
collective.viewlet.banner.egg-info/PKG-INFO
collective.viewlet.banner.egg-info/SOURCES.txt
collective.viewlet.banner.egg-info/dependency_links.txt
collective.viewlet.banner.egg-info/entry_points.txt
collective.viewlet.banner.egg-info/namespace_packages.txt
collective.viewlet.banner.egg-info/not-zip-safe
collective.viewlet.banner.egg-info/requires.txt
collective.viewlet.banner.egg-info/top_level.txt
collective/viewlet/__init__.py
collective/viewlet/banner/__init__.py
collective/viewlet/banner/banner_tool.py
collective/viewlet/banner/configure.zcml
collective/viewlet/banner/profiles.zcml
collective/viewlet/banner/tests.py
collective/viewlet/banner/tool.gif
collective/viewlet/banner/profiles/default/controlpanel.xml
collective/viewlet/banner/profiles/default/metadata.xml
collective/viewlet/banner/profiles/default/skins.xml
collective/viewlet/banner/profiles/default/toolset.xml
collective/viewlet/banner/skins/bannertool/prefs_bannertool_form.cpt
collective/viewlet/banner/skins/bannertool/prefs_bannertool_form.cpt.metadata
collective/viewlet/banner/skins/bannertool/prefs_bannertool_set.cpy
collective/viewlet/banner/skins/bannertool/prefs_bannertool_set.cpy.metadata
collective/viewlet/banner/skins/bannertool/prefs_bannertool_validate.vpy
docs/HISTORY.txt
docs/INSTALL.txt
docs/LICENSE.GPL
docs/LICENSE.txt