Metadata-Version: 1.0
Name: collective.viewlet.banner
Version: 0.1a
Summary: A tool for configuring banners displayed using viewlets
Home-page: http://svn.plone.org/svn/collective/collective.viewlet.banner
Author: Raphael Ritz and Robin Harms Oredsson
Author-email: raphael.ritz@incf.org
License: GPL
Keywords: viewlet banner configuration
Platform: UNKNOWN
Classifier: Framework :: Plone
Classifier: Programming Language :: Python
Classifier: Topic :: Software Development :: Libraries :: Python Modules
Classifier: Development Status :: 3 - Alpha
